langchain_llm_config/__init__.py
langchain_llm_config/cli.py
langchain_llm_config/config.py
langchain_llm_config/config_utils.py
langchain_llm_config/factory.py
langchain_llm_config/.tiktoken_cache/9b5ad71b2ce5302211f9c61530b329a4922fc6a4
langchain_llm_config/assistant/__init__.py
langchain_llm_config/assistant/base.py
langchain_llm_config/assistant/multimodal.py
langchain_llm_config/assistant/providers/__init__.py
langchain_llm_config/assistant/providers/gemini.py
langchain_llm_config/assistant/providers/kunlun.py
langchain_llm_config/assistant/providers/openai.py
langchain_llm_config/assistant/providers/vllm.py
langchain_llm_config/embeddings/__init__.py
langchain_llm_config/embeddings/base.py
langchain_llm_config/embeddings/providers/__init__.py
langchain_llm_config/embeddings/providers/gemini.py
langchain_llm_config/embeddings/providers/infinity.py
langchain_llm_config/embeddings/providers/kunlun.py
langchain_llm_config/embeddings/providers/openai.py
langchain_llm_config/embeddings/providers/vllm.py
langchain_llm_config/templates/api.yaml
langchain_llm_config/templates/api_v2.yaml
langchain_llm_config-0.3.2.dist-info/METADATA
langchain_llm_config-0.3.2.dist-info/WHEEL
langchain_llm_config-0.3.2.dist-info/entry_points.txt
langchain_llm_config-0.3.2.dist-info/licenses/LICENSE
langchain_llm_config-0.3.2.dist-info/RECORD
