Metadata-Version: 2.4
Name: langchain-llm-config
Version: 0.3.2
Summary: A comprehensive LLM configuration package supporting multiple providers (OpenAI, VLLM, Gemini, Infinity) for chat assistants and embeddings
Project-URL: Homepage, https://github.com/liux2/Langchain-LLM-Config
Project-URL: Repository, https://github.com/liux2/Langchain-LLM-Config
Project-URL: Documentation, https://github.com/liux2/Langchain-LLM-Config#readme
Project-URL: Bug Tracker, https://github.com/liux2/Langchain-LLM-Config/issues
Author-email: Xingbang Liu <xingbangliu48@gmail.com>
License: MIT
License-File: LICENSE
Keywords: assistant,chat,embeddings,gemini,langchain,llm,openai,vllm
Classifier: Development Status :: 3 - Alpha
Classifier: Intended Audience :: Developers
Classifier: License :: OSI Approved :: MIT License
Classifier: Operating System :: OS Independent
Classifier: Programming Language :: Python :: 3
Classifier: Programming Language :: Python :: 3.9
Classifier: Programming Language :: Python :: 3.10
Classifier: Programming Language :: Python :: 3.11
Classifier: Topic :: Scientific/Engineering :: Artificial Intelligence
Classifier: Topic :: Software Development :: Libraries :: Python Modules
Requires-Python: >=3.9
Requires-Dist: langchain-core>=0.1.0
Requires-Dist: pydantic>=2.0.0
Requires-Dist: python-dotenv>=1.0.0
Requires-Dist: pyyaml>=6.0
Provides-Extra: all
Requires-Dist: langchain-community>=0.1.0; extra == 'all'
Requires-Dist: langchain-community>=0.3.27; extra == 'all'
Requires-Dist: langchain-google-genai>=2.0.10; extra == 'all'
Requires-Dist: langchain-openai>=0.1.0; extra == 'all'
Requires-Dist: openai>=1.0.0; extra == 'all'
Requires-Dist: sentence-transformers>=2.2.0; extra == 'all'
Provides-Extra: assistants
Requires-Dist: langchain-community>=0.3.27; extra == 'assistants'
Requires-Dist: langchain-google-genai>=2.0.10; extra == 'assistants'
Requires-Dist: langchain-openai>=0.1.0; extra == 'assistants'
Requires-Dist: openai>=1.0.0; extra == 'assistants'
Provides-Extra: dev
Requires-Dist: black>=23.0.0; extra == 'dev'
Requires-Dist: build>=1.2.2.post1; extra == 'dev'
Requires-Dist: flake8>=7.0.0; extra == 'dev'
Requires-Dist: isort>=5.12.0; extra == 'dev'
Requires-Dist: mypy>=1.0.0; extra == 'dev'
Requires-Dist: pyflakes>=3.2.0; extra == 'dev'
Requires-Dist: pytest-mypy>=1.0.1; extra == 'dev'
Requires-Dist: twine>=6.1.0; extra == 'dev'
Requires-Dist: types-pyyaml>=6.0.12.20250516; extra == 'dev'
Provides-Extra: embeddings
Requires-Dist: langchain-community>=0.1.0; extra == 'embeddings'
Requires-Dist: sentence-transformers>=2.2.0; extra == 'embeddings'
Provides-Extra: gemini
Requires-Dist: langchain-google-genai>=2.0.10; extra == 'gemini'
Provides-Extra: infinity
Requires-Dist: langchain-community>=0.1.0; extra == 'infinity'
Provides-Extra: local-models
Requires-Dist: sentence-transformers>=2.2.0; extra == 'local-models'
Provides-Extra: openai
Requires-Dist: langchain-openai>=0.1.0; extra == 'openai'
Requires-Dist: openai>=1.0.0; extra == 'openai'
Provides-Extra: test
Requires-Dist: pytest-asyncio>=0.21.0; extra == 'test'
Requires-Dist: pytest-cov>=4.0.0; extra == 'test'
Requires-Dist: pytest>=7.0.0; extra == 'test'
Provides-Extra: vllm
Requires-Dist: langchain-community>=0.3.27; extra == 'vllm'
